Metadata-Version: 2.1
Name: akari-dl
Version: 1.2.2
Summary: A lightweight and open-source anime downloading CLI.
Home-page: https://github.com/keisanng/akari-dl
Author: keisan
Author-email: <keisan@skiff.com>
Project-URL: Documentation, https://github.com/keisanng/akari-dl#readme
Project-URL: Tracker, https://github.com/users/keisanng/projects/3
Requires-Python: >=3.10
License-File: LICENSE
